{
    "total_count": 32,
    "total_uniques": 20,
    "daily_breakdown": [
        {
            "date": "2025-09-09T00:00:00Z",
            "count": 4,
            "uniques": 3
        },
        {
            "date": "2025-09-12T00:00:00Z",
            "count": 5,
            "uniques": 4
        },
        {
            "date": "2025-09-13T00:00:00Z",
            "count": 1,
            "uniques": 1
        },
        {
            "date": "2025-09-15T00:00:00Z",
            "count": 6,
            "uniques": 6
        },
        {
            "date": "2025-09-16T00:00:00Z",
            "count": 8,
            "uniques": 4
        },
        {
            "date": "2025-09-17T00:00:00Z",
            "count": 2,
            "uniques": 1
        },
        {
            "date": "2025-09-18T00:00:00Z",
            "count": 4,
            "uniques": 3
        },
        {
            "date": "2025-09-19T00:00:00Z",
            "count": 1,
            "uniques": 1
        },
        {
            "date": "2025-09-20T00:00:00Z",
            "count": 1,
            "uniques": 1
        }
    ]
}